[
    {
        "title": "Javascript Fullstack",
        "location": "FST of the University of Lille (France)",
        "url": "https://www.fil.univ-lille.fr/portail/index.php?dipl=L&sem=S6&ue=JSFS&label=Pr%C3%A9sentation",
        "year": "2024-2025"
    },
    {
        "title": "Interaction Humain-Machine",
        "location": "FST of the University of Lille (France)",
        "url": "https://www.fil.univ-lille.fr/portail/index.php?dipl=L&sem=S5&ue=IHM&label=Pr%C3%A9sentation",
        "year": "2024-2025"
    },
    {
        "title": "Interaction Humain-Machine",
        "location": "FST of the University of Lille (France)",
        "url": "https://www.fil.univ-lille.fr/portail/index.php?dipl=L&sem=S5&ue=IHM&label=Pr%C3%A9sentation",
        "year": "2023-2024"
    }
]